{"file":"xuanwu_idle.png","frames":{
"idle_1_body_00":{"x":813,"y":549,"w":130,"h":104,"offX":92,"offY":127,"sourceW":320,"sourceH":320},
"idle_1_body_01":{"x":259,"y":382,"w":138,"h":101,"offX":91,"offY":130,"sourceW":320,"sourceH":320},
"idle_1_body_02":{"x":539,"y":352,"w":144,"h":99,"offX":90,"offY":132,"sourceW":320,"sourceH":320},
"idle_1_body_03":{"x":685,"y":449,"w":148,"h":95,"offX":90,"offY":135,"sourceW":320,"sourceH":320},
"idle_1_body_04":{"x":836,"y":355,"w":149,"h":95,"offX":91,"offY":135,"sourceW":320,"sourceH":320},
"idle_1_body_05":{"x":539,"y":254,"w":150,"h":96,"offX":92,"offY":134,"sourceW":320,"sourceH":320},
"idle_1_body_06":{"x":539,"y":453,"w":135,"h":101,"offX":93,"offY":129,"sourceW":320,"sourceH":320},
"idle_1_body_07":{"x":132,"y":383,"w":124,"h":107,"offX":93,"offY":124,"sourceW":320,"sourceH":320},
"idle_3_body_00":{"x":0,"y":385,"w":130,"h":104,"offX":98,"offY":127,"sourceW":320,"sourceH":320},
"idle_3_body_01":{"x":399,"y":382,"w":138,"h":101,"offX":91,"offY":130,"sourceW":320,"sourceH":320},
"idle_3_body_02":{"x":843,"y":254,"w":144,"h":99,"offX":86,"offY":132,"sourceW":320,"sourceH":320},
"idle_3_body_03":{"x":835,"y":452,"w":148,"h":95,"offX":82,"offY":135,"sourceW":320,"sourceH":320},
"idle_3_body_04":{"x":685,"y":352,"w":149,"h":95,"offX":80,"offY":135,"sourceW":320,"sourceH":320},
"idle_3_body_05":{"x":691,"y":254,"w":150,"h":96,"offX":78,"offY":134,"sourceW":320,"sourceH":320},
"idle_3_body_06":{"x":676,"y":546,"w":135,"h":101,"offX":92,"offY":129,"sourceW":320,"sourceH":320},
"idle_3_body_07":{"x":0,"y":491,"w":124,"h":107,"offX":103,"offY":124,"sourceW":320,"sourceH":320},
"idle_5_body_00":{"x":280,"y":254,"w":130,"h":126,"offX":98,"offY":111,"sourceW":320,"sourceH":320},
"idle_5_body_01":{"x":0,"y":128,"w":138,"h":127,"offX":91,"offY":111,"sourceW":320,"sourceH":320},
"idle_5_body_02":{"x":756,"y":127,"w":144,"h":125,"offX":85,"offY":112,"sourceW":320,"sourceH":320},
"idle_5_body_03":{"x":610,"y":0,"w":149,"h":125,"offX":81,"offY":111,"sourceW":320,"sourceH":320},
"idle_5_body_04":{"x":458,"y":0,"w":150,"h":126,"offX":79,"offY":110,"sourceW":320,"sourceH":320},
"idle_5_body_05":{"x":0,"y":0,"w":151,"h":126,"offX":77,"offY":110,"sourceW":320,"sourceH":320},
"idle_5_body_06":{"x":280,"y":128,"w":136,"h":124,"offX":91,"offY":112,"sourceW":320,"sourceH":320},
"idle_5_body_07":{"x":132,"y":257,"w":125,"h":124,"offX":102,"offY":112,"sourceW":320,"sourceH":320},
"idle_7_body_00":{"x":0,"y":257,"w":130,"h":126,"offX":92,"offY":111,"sourceW":320,"sourceH":320},
"idle_7_body_01":{"x":140,"y":128,"w":138,"h":127,"offX":91,"offY":111,"sourceW":320,"sourceH":320},
"idle_7_body_02":{"x":610,"y":127,"w":144,"h":125,"offX":91,"offY":112,"sourceW":320,"sourceH":320},
"idle_7_body_03":{"x":761,"y":0,"w":149,"h":125,"offX":90,"offY":111,"sourceW":320,"sourceH":320},
"idle_7_body_04":{"x":306,"y":0,"w":150,"h":126,"offX":91,"offY":110,"sourceW":320,"sourceH":320},
"idle_7_body_05":{"x":153,"y":0,"w":151,"h":126,"offX":92,"offY":110,"sourceW":320,"sourceH":320},
"idle_7_body_06":{"x":418,"y":128,"w":136,"h":124,"offX":93,"offY":112,"sourceW":320,"sourceH":320},
"idle_7_body_07":{"x":412,"y":254,"w":125,"h":124,"offX":93,"offY":112,"sourceW":320,"sourceH":320}}}